{
  "thumbnail": "https://res.cloudinary.com/paulcloud/image/upload/v1636708818/imper/WhatsApp_Image_2021-11-12_at_10.15.36_ijxum4.jpg",
  "title": "Impermeabilización de terraza con bicapa autoprotegida en Sant Cugat del Vallès",
  "service": "Impermeabilizaciones de terrazas y cubiertas",
  "seoDescription": "Para la impermeabilización de esta terraza en Sant Cugat del Vallès, se ha optado por el sistema de impermeabilización con bicapa autoprotegida con acabado mineral, creando zonas específicas de paso para los técnicos favoreciendo así la mayor durabilidad de los materiales. ",
  "date": "12 Nov 2021",
  "place": "Sant Cugat del Vallès"
}
